tfip2023_dist/__init__.py
tfip2023_dist-0.0.1.dist-info/LICENSE
tfip2023_dist-0.0.1.dist-info/METADATA
tfip2023_dist-0.0.1.dist-info/WHEEL
tfip2023_dist-0.0.1.dist-info/top_level.txt
tfip2023_dist-0.0.1.dist-info/RECORD
