Metadata-Version: 2.1
Name: tfip2023_dist
Version: 0.0.1
Summary: Any description you can put
Home-page: https://github.com/Dr-WangZhiyuan/tfip2023_dist
Author: Dr. Zhiyuan Wang
Author-email: wang1399@e.ntu.edu.sg
License: MIT
Classifier: Programming Language :: Python :: 3
Classifier: License :: OSI Approved :: MIT License
License-File: LICENSE
Requires-Dist: numpy
